findr/__init__.py
findr/auto.py
findr/common.py
findr/examples.py
findr/netr.py
findr/osdepend.py
findr/pij.py
findr/types.py
findr/data/geuvadis/dc.dat
findr/data/geuvadis/dgmi.dat
findr/data/geuvadis/dgt.dat
findr/data/geuvadis/dmi.dat
findr/data/geuvadis/dt.dat
findr/data/geuvadis/dt2.dat
findr/data/geuvadis/namest.txt
findr-1.0.8.dist-info/LICENSE
findr-1.0.8.dist-info/METADATA
findr-1.0.8.dist-info/WHEEL
findr-1.0.8.dist-info/top_level.txt
findr-1.0.8.dist-info/RECORD
