Metadata-Version: 2.1
Name: findr
Version: 1.0.8
Summary: Fast Inference of Networks from Directed Regulations
Home-page: https://github.com/lingfeiwang/findr-python
Author: Lingfei Wang
Author-email: Lingfei.Wang.github@outlook.com
License: AGPL-3
Download-URL: https://github.com/lingfeiwang/findr-python
Platform: UNKNOWN
Classifier: Development Status :: 5 - Production/Stable
Classifier: License :: OSI Approved :: GNU Affero General Public License v3
Classifier: Environment :: Console
Classifier: Intended Audience :: End Users/Desktop
Classifier: Intended Audience :: Science/Research
Classifier: Operating System :: OS Independent
Classifier: Programming Language :: Python :: 2
Classifier: Programming Language :: Python :: 3
Classifier: Topic :: Scientific/Engineering :: Bio-Informatics
Classifier: Topic :: Software Development :: User Interfaces
Requires-Dist: numpy
